{
    "paths": [
        {
            "name": "/vend",
            "lambdaFunction": "VendRouteLambda",
            "privacy": {
                "protected": true,
                "auth": [
                    "/POST",
                    "/GET",
                    "/PUT",
                    "/PATCH",
                    "/DELETE"
                ],
                "unauth": [
                    "/POST",
                    "/GET",
                    "/PUT",
                    "/PATCH",
                    "/DELETE"
                ]
            }
        },
        {
            "name": "/vend",
            "lambdaFunction": "VendRouteLambda",
            "privacy": {
                "protected": true,
                "auth": [
                    "/POST",
                    "/GET",
                    "/PUT",
                    "/PATCH",
                    "/DELETE"
                ],
                "unauth": [
                    "/POST",
                    "/GET",
                    "/PUT",
                    "/PATCH",
                    "/DELETE"
                ]
            }
        }
    ],
    "resourceName": "VendRouteRest",
    "apiName": "VendRouteRest",
    "functionArns": [
        {
            "lambdaFunction": "VendRouteLambda"
        }
    ],
    "privacy": {
        "auth": 1,
        "unauth": 1,
        "authRoleName": "amplify-vendroute-dev-184922-authRole",
        "unAuthRoleName": "amplify-vendroute-dev-184922-unauthRole"
    },
    "dependsOn": [
        {
            "category": "function",
            "resourceName": "VendRouteLambda",
            "attributes": [
                "Name",
                "Arn"
            ]
        }
    ]
}
